research_framework/__init__.py
research_framework/base/__init__.py
research_framework/base/container/__init__.py
research_framework/base/container/base_container.py
research_framework/base/container/model/__init__.py
research_framework/base/container/model/bind_model.py
research_framework/base/flyweight/__init__.py
research_framework/base/flyweight/base_flyweight.py
research_framework/base/flyweight/base_flyweight_manager.py
research_framework/base/model/__init__.py
research_framework/base/model/base_dao.py
research_framework/base/model/base_utils.py
research_framework/base/pipeline/__init__.py
research_framework/base/pipeline/base_pipeline.py
research_framework/base/plugin/__init__.py
research_framework/base/plugin/base_plugin.py
research_framework/base/plugin/base_wrapper.py
research_framework/base/singleton/__init__.py
research_framework/base/singleton/base_singleton.py
research_framework/base/storage/__init__.py
research_framework/base/storage/base_storage.py
research_framework/base/utils/__init__.py
research_framework/base/utils/grid_seach.py
research_framework/base/utils/method_overload.py
research_framework/container/__init__.py
research_framework/container/bind_manager.py
research_framework/container/container.py
research_framework/container/model/__init__.py
research_framework/container/model/global_config.py
research_framework/dataset/__init__.py
research_framework/dataset/basic_dataset.py
research_framework/dataset/standard_dataset.py
research_framework/flyweight/__init__.py
research_framework/flyweight/flyweight.py
research_framework/flyweight/flyweight_manager.py
research_framework/flyweight/mem_manager.py
research_framework/flyweight/model/__init__.py
research_framework/flyweight/model/item_dao.py
research_framework/flyweight/model/item_model.py
research_framework/flyweight/model/item_simple_model.py
research_framework/neural_models/__init__.py
research_framework/neural_models/doomy_model.py
research_framework/pipeline/__init__.py
research_framework-0.2.30.dist-info/LICENSE
research_framework-0.2.30.dist-info/METADATA
research_framework-0.2.30.dist-info/WHEEL
research_framework-0.2.30.dist-info/top_level.txt
research_framework-0.2.30.dist-info/RECORD
